BBN/BBN.py
BBN/__init__.py
BBN/constants.py
BBN/expansion.py
BBN/nuclear.py
BBN-0.0.1.dist-info/LICENSE
BBN-0.0.1.dist-info/METADATA
BBN-0.0.1.dist-info/WHEEL
BBN-0.0.1.dist-info/top_level.txt
BBN-0.0.1.dist-info/RECORD
