Metadata-Version: 2.1
Name: BBN
Version: 0.0.1
Summary: Big Bang Nucleosynthesis
Home-page: https://github.com/tt-nakamura/BBN
Author: tt-nakamura
Author-email: a41757@gmail.com
License: UNKNOWN
Project-URL: Bug Tracker, https://github.com/tt-nakamura/BBN/issues
Platform: UNKNOWN
Classifier: Programming Language :: Python :: 3
Classifier: License :: OSI Approved :: MIT License
Classifier: Operating System :: OS Independent
Requires-Python: >=3.6
